similarity_check/Similarity.py
similarity_check/__init__.py
simscore-28.8.1.dist-info/LICENSE.txt
simscore-28.8.1.dist-info/METADATA
simscore-28.8.1.dist-info/WHEEL
simscore-28.8.1.dist-info/top_level.txt
simscore-28.8.1.dist-info/RECORD
